hello_8trider-0.5.1.dist-info/METADATA
hello_8trider-0.5.1.dist-info/WHEEL
hello_8trider-0.5.1.dist-info/entry_points.txt
hello_8trider/__init__.py
hello_8trider/my.py
hello_8trider/who.py
hello_8trider-0.5.1.dist-info/RECORD
