Metadata-Version: 2.1
Name: hello-8trider
Version: 0.5.1
Author-Email: 8trider <8trider@naver.com>
License: MIT
Project-URL: Homepage, https://github.com/8trider/hello
Project-URL: Bug tracker, https://github.com/8trider/hello/issues
Requires-Python: >=3.8
